maestro/__init__.py
maestro/__main__.py
maestro/audit.py
maestro/entities.py
maestro/environment.py
maestro/exceptions.py
maestro/guestutils.py
maestro/lifecycle.py
maestro/loader.py
maestro/maestro.py
maestro/shipproviders.py
maestro/termoutput.py
maestro/version.py
maestro/extensions/__init__.py
maestro/extensions/logging/__init__.py
maestro/extensions/logging/logstash.py
maestro/plays/__init__.py
maestro/plays/tasks.py
tests/__init__.py
tests/unittests.py
maestro_ng-0.8.3.dist-info/LICENSE
maestro_ng-0.8.3.dist-info/METADATA
maestro_ng-0.8.3.dist-info/WHEEL
maestro_ng-0.8.3.dist-info/entry_points.txt
maestro_ng-0.8.3.dist-info/pbr.json
maestro_ng-0.8.3.dist-info/top_level.txt
maestro_ng-0.8.3.dist-info/zip-safe
maestro_ng-0.8.3.dist-info/RECORD
