Metadata-Version: 2.1
Name: maestro-ng
Version: 0.8.3
Summary: Orchestrator for multi-host Docker deployments
Home-page: https://github.com/signalfx/maestro-ng
Author: Maxime Petazzoni
Author-email: max@signalfx.com
License: Apache Software License v2
Keywords: maestro docker orchestration deployment
Classifier: Development Status :: 3 - Alpha
Classifier: Environment :: Console
Classifier: Intended Audience :: Developers
Classifier: Operating System :: OS Independent
Classifier: Programming Language :: Python
Classifier: Topic :: Utilities
License-File: LICENSE
Requires-Dist: docker-py (>=1.4.0)
Requires-Dist: pyyaml
Requires-Dist: jinja2
Requires-Dist: six
Requires-Dist: bgtunnel
Requires-Dist: python-simple-hipchat
Requires-Dist: slacker
Requires-Dist: requests (>=2.7.0)
Requires-Dist: netifaces
